teamhack_db/__init__.py
teamhack_db/__main__.py
teamhack_db/cli.py
teamhack_db/conf.py
teamhack_db/sql.py
teamhack_dns/__init__.py
teamhack_dns/__main__.py
teamhack_dns/server.py
teamhack_rest/__init__.py
teamhack_rest/__main__.py
teamhack-0.0.41.dist-info/METADATA
teamhack-0.0.41.dist-info/WHEEL
teamhack-0.0.41.dist-info/top_level.txt
teamhack-0.0.41.dist-info/RECORD
